pineappledb/__init__.py
pineappledb/__main__.py
pineappledb/host_pine.py
pineappledb/pine.py
pineappledb/pineapple.py
pineappledb/setup.py
pineappledb/test.py
pineappledb/databases/AMBA.db
pineappledb/databases/EMMY.db
pineappledb/databases/HOZANA.db
pineappledb/databases/mangoo.db
pineappledb/databases/readme
pineappledb/databases/sa.db
pineappledb/databases/sda.db
pineappledb/databases/simba.db
pineappledb/static/css/bootstrap.min.css
pineappledb/static/css/sqlbrowse.css
pineappledb/static/css/style.css
pineappledb/static/css/syntax-highlight.css
pineappledb/static/fonts/glyphicons-halflings-regular.eot
pineappledb/static/fonts/glyphicons-halflings-regular.svg
pineappledb/static/fonts/glyphicons-halflings-regular.ttf
pineappledb/static/fonts/glyphicons-halflings-regular.woff
pineappledb/static/img/delete.png
pineappledb/static/img/expression.png
pineappledb/static/img/index-create.png
pineappledb/static/img/index-drop.png
pineappledb/static/img/insert.png
pineappledb/static/img/select-advanced.png
pineappledb/static/img/select.png
pineappledb/static/img/table-alter.png
pineappledb/static/img/table-create.png
pineappledb/static/img/table-drop.png
pineappledb/static/img/trigger-create.png
pineappledb/static/img/trigger-drop.png
pineappledb/static/img/update.png
pineappledb/static/img/view-create.png
pineappledb/static/img/view-drop.png
pineappledb/static/js/app.js
pineappledb/static/js/bootstrap.bundle.min.js
pineappledb/static/js/jquery-1.11.0.min.js
pineappledb/static/js/pine.js
pineappledb/static/logo/pine-apple-logo.png
pineappledb/static/logo/pine-apple-logo2.png
pineappledb/system_db/pinedb.db
pineappledb/templates/add_column.html
pineappledb/templates/add_index.html
pineappledb/templates/base.html
pineappledb/templates/base_table.html
pineappledb/templates/base_tables.html
pineappledb/templates/dashboard.html
pineappledb/templates/drop_column.html
pineappledb/templates/drop_index.html
pineappledb/templates/drop_table.html
pineappledb-0.1.6.dist-info/LICENCE
pineappledb-0.1.6.dist-info/METADATA
pineappledb-0.1.6.dist-info/WHEEL
pineappledb-0.1.6.dist-info/top_level.txt
pineappledb-0.1.6.dist-info/RECORD
